easy_mlops/__init__.py
easy_mlops/cli.py
easy_mlops/pipeline.py
easy_mlops/config/__init__.py
easy_mlops/config/config.py
easy_mlops/deployment/__init__.py
easy_mlops/deployment/deployer.py
easy_mlops/deployment/steps.py
easy_mlops/distributed/__init__.py
easy_mlops/distributed/errors.py
easy_mlops/distributed/master.py
easy_mlops/distributed/state.py
easy_mlops/distributed/task_runner.py
easy_mlops/distributed/worker.py
easy_mlops/observability/__init__.py
easy_mlops/observability/monitor.py
easy_mlops/observability/steps.py
easy_mlops/preprocessing/__init__.py
easy_mlops/preprocessing/preprocessor.py
easy_mlops/preprocessing/steps.py
easy_mlops/training/__init__.py
easy_mlops/training/backends.py
easy_mlops/training/trainer.py
make_mlops_easy-0.4.0.dist-info/licenses/LICENSE
make_mlops_easy-0.4.0.dist-info/METADATA
make_mlops_easy-0.4.0.dist-info/WHEEL
make_mlops_easy-0.4.0.dist-info/entry_points.txt
make_mlops_easy-0.4.0.dist-info/top_level.txt
make_mlops_easy-0.4.0.dist-info/RECORD
