Metadata-Version: 2.4
Name: make-mlops-easy
Version: 0.4.0
Summary: Make MLOps easier with an AI-powered framework
Author-email: Umberto Domenico Ciccia <umbertociccia@icloud.com>
License: MIT
Project-URL: Homepage, https://github.com/umbertocicciaa/easy-mlops
Project-URL: Repository, https://github.com/umbertocicciaa/easy-mlops
Project-URL: Issues, https://github.com/umbertocicciaa/easy-mlops/issues
Keywords: mlops,machine-learning,ai,automation,deployment
Classifier: Development Status :: 3 - Alpha
Classifier: Intended Audience :: Developers
Classifier: Topic :: Scientific/Engineering :: Artificial Intelligence
Classifier: License :: OSI Approved :: MIT License
Classifier: Programming Language :: Python :: 3.10
Classifier: Programming Language :: Python :: 3.11
Requires-Python: >=3.10
License-File: LICENSE
Requires-Dist: click>=8.0.0
Requires-Dist: pandas>=1.3.0
Requires-Dist: scikit-learn>=1.0.0
Requires-Dist: joblib>=1.0.0
Requires-Dist: pyyaml>=6.0
Requires-Dist: rich>=10.0.0
Requires-Dist: xgboost>=3.0.0
Requires-Dist: fastapi>=0.110.0
Requires-Dist: uvicorn>=0.23.0
Requires-Dist: requests>=2.31.0
Provides-Extra: dev
Requires-Dist: pytest>=7.0.0; extra == "dev"
Requires-Dist: pytest-cov>=3.0.0; extra == "dev"
Requires-Dist: black>=22.0.0; extra == "dev"
Requires-Dist: flake8>=4.0.0; extra == "dev"
Requires-Dist: mypy>=0.950; extra == "dev"
Requires-Dist: mkdocs>=1.5.0; extra == "dev"
Requires-Dist: mkdocs-material>=9.0.0; extra == "dev"
Requires-Dist: mkdocs-git-revision-date-localized-plugin>=1.2.0; extra == "dev"
Dynamic: license-file
